agent_code_squad/__init__.py
agent_code_squad/cli.py
agent_code_squad/config.py
agent_code_squad/context.py
agent_code_squad/core/__init__.py
agent_code_squad/core/execution.py
agent_code_squad/core/scopes.py
agent_code_squad/core/supervisor.py
agent_code_squad/dispatch.py
agent_code_squad/event_utils.py
agent_code_squad/ops_log.py
agent_code_squad/paths.py
agent_code_squad/runner.py
agent_code_squad/server.py
agent_code_squad/shared_kb.py
agent_code_squad/tools.py
agent_code_squad/utils.py
agent_code_squad-0.1.19.dist-info/METADATA
agent_code_squad-0.1.19.dist-info/WHEEL
agent_code_squad-0.1.19.dist-info/entry_points.txt
agent_code_squad-0.1.19.dist-info/RECORD
