Metadata-Version: 2.4
Name: agent-code-squad
Version: 0.1.19
Summary: MCP server for orchestrating multi-subagent code runs with minimized context and patch-only outputs.
License: MIT
Author: dzrlab
Requires-Python: >=3.10,<4.0
Classifier: License :: OSI Approved :: MIT License
Classifier: Programming Language :: Python :: 3
Classifier: Programming Language :: Python :: 3.10
Classifier: Programming Language :: Python :: 3.11
Classifier: Programming Language :: Python :: 3.12
Classifier: Programming Language :: Python :: 3.13
Classifier: Programming Language :: Python :: 3.14
Requires-Dist: mcp (==1.25.0)
Project-URL: Homepage, https://example.invalid/agent-code-squad
